django_url_params-1.0.2.dist-info/DESCRIPTION.rst
django_url_params-1.0.2.dist-info/METADATA
django_url_params-1.0.2.dist-info/RECORD
django_url_params-1.0.2.dist-info/WHEEL
django_url_params-1.0.2.dist-info/metadata.json
django_url_params-1.0.2.dist-info/top_level.txt
urlparams/__init__.py
urlparams/redirect.py
